{
  "艾尔文": {
    "type": "步兵",
    "pro":"战士",
    "exp": 0,
    "avatar":"asset/image/avatar/face01.gif",
    "avatars":{
      "hurt":"asset/image/avatar/face02.gif",
      "angry":"asset/image/avatar/face03.gif",
      "heavy":"asset/image/avatar/face04.gif"
    },
    "img": "asset/image/role/hero/common/mgif0101.png",
    "imgs": {
      "active":"asset/image/role/hero/active/mgif0101.gif",
      "battle":"asset/image/role/hero/battle/class0101.gif"
    },
    "atk": 23,
    "def": 18,
    "mov": 5,
    "mr": 50,
    "mp": 0,
    "range":1,
    "move": "run",
    "command":{
      "range": 2,
      "atk": 1,
      "def": 3
    },
    "magic":[],
    "magic_atk":1,
    "magic_range":0,
    "equip":{
      "weapon":null,
      "armor":null,
      "jew":null
    },
    "recruit":["步兵"],
    "inj":"asset/effect/injured-man.mp3"
  },
  "海恩":{
    "type":"法师",
    "pro":"术士",
    "exp": 0,
    "avatar":"asset/image/avatar/face11.gif",
    "avatars":{
      "hurt":"asset/image/avatar/face12.gif",
      "angry":"asset/image/avatar/face13.gif",
      "heavy":"asset/image/avatar/face14.gif"
    },
    "img": "asset/image/role/hero/common/mgif0503.png",
    "imgs": {
      "active":"asset/image/role/hero/active/mgif0503.gif",
      "battle":"asset/image/role/hero/battle/class0503.gif"
    },
    "atk":23,
    "def":13,
    "mov":5,
    "mr":60,
    "mp":12,
    "range":1,
    "move":"run",
    "command":{
      "range":2,
      "atk":4,
      "def":2
    },
    "magic":["魔法箭"],
    "magic_atk":1,
    "magic_range":0,
    "equip":{
      "weapon":null,
      "armor":null,
      "jew":null
    },
    "recruit":["卫兵"],
    "inj":"asset/effect/injured-man.mp3"
  },
  "雪莉":{
    "type":"步兵",
    "pro":"战士",
    "exp": 0,
    "avatar":"asset/image/avatar/face0d.gif",
    "avatars":{
      "hurt":"asset/image/avatar/face0e.gif",
      "angry":"asset/image/avatar/face0f.gif",
      "heavy":"asset/image/avatar/face10.gif"
    },
    "img": "asset/image/role/hero/common/mgif0401.png",
    "imgs": {
      "active":"asset/image/role/hero/active/mgif0401.gif",
      "battle":"asset/image/role/hero/battle/class0401.gif"
    },
    "atk":21,
    "def":18,
    "mov":5,
    "mr":50,
    "mp":0,
    "range":1,
    "move":"run",
    "command":{
      "range":2,
      "atk":2,
      "def":2
    },
    "magic":[],
    "magic_atk":1,
    "magic_range":0,
    "equip":{
      "weapon":null,
      "armor":null,
      "jew":null
    },
    "recruit":["步兵"],
    "inj":"asset/effect/injured-woman.mp3"
  },
  "阿伦":{
    "type":"步兵",
    "pro":"战士",
    "exp": 0,
    "avatar":"asset/image/avatar/face25.gif",
    "avatars":{
      "hurt":"asset/image/avatar/face26.gif",
      "angry":"asset/image/avatar/face27.gif",
      "heavy":"asset/image/avatar/face28.gif"
    },
    "img": "asset/image/role/hero/common/mgif0801.png",
    "imgs": {
      "active":"asset/image/role/hero/active/mgif0801.gif",
      "battle":"asset/image/role/hero/battle/class0801.gif"
    },
    "atk":22,
    "def":18,
    "mov":5,
    "mr":50,
    "mp":0,
    "range":1,
    "move":"run",
    "command":{
      "range":2,
      "atk":1,
      "def":2
    },
    "magic":[],
    "magic_atk":1,
    "magic_range":0,
    "equip":{
      "weapon":null,
      "armor":null,
      "jew":null
    },
    "recruit":["步兵"],
    "inj":"asset/effect/injured-man.mp3"
  },
  "基斯":{
    "type":"步兵",
    "pro":"战士",
    "exp": 0,
    "avatar":"asset/image/avatar/face21.gif",
    "avatars":{
      "hurt":"asset/image/avatar/face22.gif",
      "angry":"asset/image/avatar/face23.gif",
      "heavy":"asset/image/avatar/face24.gif"
    },
    "img": "asset/image/role/hero/common/mgif0701.png",
    "imgs": {
      "active":"asset/image/role/hero/active/mgif0701.gif",
      "battle":"asset/image/role/hero/battle/class0701.gif"
    },
    "atk":21,
    "def":18,
    "mov":5,
    "mr":50,
    "mp":0,
    "range":1,
    "move":"run",
    "command":{
      "range":2,
      "atk":0,
      "def":4
    },
    "magic":[],
    "magic_atk":1,
    "magic_range":0,
    "equip":{
      "weapon":null,
      "armor":null,
      "jew":null
    },
    "recruit":["步兵"],
    "inj":"asset/effect/injured-man.mp3"
  },
  "雷斯塔":{
    "type":"步兵",
    "pro":"战士",
    "exp": 0,
    "avatar":"asset/image/avatar/face1d.gif",
    "avatars":{
      "hurt":"asset/image/avatar/face1e.gif",
      "angry":"asset/image/avatar/face1f.gif",
      "heavy":"asset/image/avatar/face20.gif"
    },
    "img": "asset/image/role/hero/common/mgif0901.png",
    "imgs": {
      "active":"asset/image/role/hero/active/mgif0901.gif",
      "battle":"asset/image/role/hero/battle/class0901.gif"
    },
    "atk":21,
    "def":18,
    "mov":5,
    "mr":50,
    "mp":0,
    "range":1,
    "move":"run",
    "command":{
      "range":2,
      "atk":0,
      "def":4
    },
    "magic":[],
    "magic_atk":1,
    "magic_range":0,
    "equip":{
      "weapon":null,
      "armor":null,
      "jew":null
    },
    "recruit":["步兵"],
    "inj":"asset/effect/injured-man.mp3"
  },
  "斯科特":{
    "type":"步兵",
    "pro":"战士",
    "exp": 0,
    "avatar":"asset/image/avatar/face15.gif",
    "avatars":{
      "hurt":"asset/image/avatar/face16.gif",
      "angry":"asset/image/avatar/face17.gif",
      "heavy":"asset/image/avatar/face18.gif"
    },
    "img": "asset/image/role/hero/common/mgif0601.png",
    "imgs": {
      "active":"asset/image/role/hero/active/mgif0601.gif",
      "battle":"asset/image/role/hero/battle/class0601.gif"
    },
    "atk":21,
    "def":18,
    "mov":5,
    "mr":50,
    "mp":0,
    "range":1,
    "move":"run",
    "command":{
      "range":2,
      "atk":2,
      "def":2
    },
    "magic":[],
    "magic_atk":1,
    "magic_range":0,
    "equip":{
      "weapon":null,
      "armor":null,
      "jew":null
    },
    "recruit":["步兵"],
    "inj":"asset/effect/injured-man.mp3"
  },
  "洁西卡":{
    "type":"法师",
    "pro":"术士",
    "exp": 0,
    "avatar":"asset/image/avatar/face19.gif",
    "avatars":{
      "hurt":"asset/image/avatar/face1a.gif",
      "angry":"asset/image/avatar/face1b.gif",
      "heavy":"asset/image/avatar/face1c.gif"
    },
    "img": "asset/image/role/hero/common/mgif0a03.png",
    "imgs": {
      "active":"asset/image/role/hero/active/mgif0a03.gif",
      "battle":"asset/image/role/hero/battle/class0a03.gif"
    },
    "atk":24,
    "def":13,
    "mov":5,
    "mr":60,
    "mp":10,
    "range":1,
    "move":"run",
    "command":{
      "range":2,
      "atk":4,
      "def":2
    },
    "magic":["魔法箭"],
    "magic_atk":1,
    "magic_range":0,
    "equip":{
      "weapon":null,
      "armor":null,
      "jew":null
    },
    "recruit":["卫兵"],
    "inj":"asset/effect/injured-woman.mp3"
  },
  "拉娜":{
    "type":"神官",
    "pro":"修女",
    "exp": 0,
    "avatar":"asset/image/avatar/face09.gif",
    "avatars":{
      "hurt":"asset/image/avatar/face0a.gif",
      "angry":"asset/image/avatar/face0b.gif",
      "heavy":"asset/image/avatar/face0c.gif"
    },
    "img": "asset/image/role/hero/common/mgif0302.png",
    "imgs": {
      "active":"asset/image/role/hero/active/mgif0302.gif",
      "battle":"asset/image/role/hero/battle/class0302.gif"
    },
    "atk":20,
    "def":20,
    "mov":5,
    "mr":70,
    "mp":5,
    "range":1,
    "move":"run",
    "command":{
      "range":2,
      "atk":2,
      "def":4
    },
    "magic":["回复1"],
    "magic_atk":1,
    "magic_range":0,
    "equip":{
      "weapon":null,
      "armor":null,
      "jew":null
    },
    "recruit":["卫兵"],
    "inj":"asset/effect/injured-woman.mp3"
  },
  "莉娅娜":{
    "type":"神官",
    "pro":"修女",
    "exp": 0,
    "avatar":"asset/image/avatar/face05.gif",
    "avatars":{
      "hurt":"asset/image/avatar/face06.gif",
      "angry":"asset/image/avatar/face07.gif",
      "heavy":"asset/image/avatar/face08.gif"
    },
    "img": "asset/image/role/hero/common/mgif0202.png",
    "imgs": {
      "active":"asset/image/role/hero/active/mgif0202.gif",
      "battle":"asset/image/role/hero/battle/class0202.gif"
    },
    "atk":20,
    "def":17,
    "mov":5,
    "mr":70,
    "mp":5,
    "range":1,
    "move":"run",
    "command":{
      "range":2,
      "atk":0,
      "def":6
    },
    "magic":["回复1"],
    "magic_atk":1,
    "magic_range":0,
    "equip":{
      "weapon":null,
      "armor":null,
      "jew":null
    },
    "recruit":["卫兵"],
    "inj":"asset/effect/injured-woman.mp3"
  },
  "罗伦":{
    "type":"步兵",
    "avatar":"asset/image/avatar/face35.gif",
    "img": "asset/image/role/hero/common/mgif99.png",
    "imgs": {
      "active":"asset/image/role/hero/active/mgif99.gif",
      "battle":"asset/image/role/hero/battle/class96.gif"
    },
    "atk":32,
    "def":30,
    "mov":5,
    "mr":50,
    "mp":6,
    "range":1,
    "move":"run",
    "command":{
      "range":3,
      "atk":3,
      "def":4
    },
    "magic":[],
    "magic_atk":1,
    "magic_range":0,
    "equip":{
      "weapon":"大剑",
      "armor":"大盾",
      "jew":null
    },
    "inj":"asset/effect/injured-man.mp3"
  },
  "步军统帅":{
    "type":"步兵",
    "avatar":"",
    "img": "asset/image/role/hero/common/mgif99.png",
    "imgs": {
      "active":"asset/image/role/hero/active/mgif99.gif",
      "battle":"asset/image/role/hero/battle/class96.gif"
    },
    "atk":25,
    "def":23,
    "mov":5,
    "mr":50,
    "mp":6,
    "range":1,
    "move":"run",
    "command":{
      "range":3,
      "atk":3,
      "def":4
    },
    "magic":[],
    "magic_atk":1,
    "magic_range":0,
    "equip":{
      "weapon":null,
      "armor":null,
      "jew":null
    },
    "recruit":["步兵","卫兵","斗士","重装步兵","枪兵","重装枪兵"],
    "inj":"asset/effect/injured-man.mp3"
  },
  "龙骑统帅":{
    "type":"骑兵",
    "avatar":"",
    "img": "asset/image/role/soldier/common/mgif69.png",
    "imgs": {
      "active":"asset/image/role/soldier/active/mgif69.gif",
      "battle":"asset/image/role/soldier/battle/class69.gif"
    },
    "atk":28,
    "def":22,
    "mov":8,
    "mr":50,
    "mp":0,
    "range":1,
    "move":"ride",
    "command":{
      "range":3,
      "atk":5,
      "def":2
    },
    "magic":[],
    "magic_atk":1,
    "magic_range":0,
    "equip":{
      "weapon":null,
      "armor":null,
      "jew":null
    },
    "recruit":["步兵","卫兵","骑兵","重装骑兵","龙骑兵"],
    "inj":"asset/effect/injured-man.mp3"
  },
  "飞龙统帅":{
    "type":"飞兵",
    "avatar":"",
    "img": "asset/image/role/hero/common/mgif4b.png",
    "imgs": {
      "active":"asset/image/role/hero/active/mgif4b.gif",
      "battle":"asset/image/role/hero/battle/class4b.gif"
    },
    "atk":27,
    "def":21,
    "mov":11,
    "mr":50,
    "mp":0,
    "range":1,
    "move":"fly",
    "command":{
      "range":3,
      "atk":4,
      "def":2
    },
    "magic":[],
    "magic_atk":1,
    "magic_range":0,
    "equip":{
      "weapon":null,
      "armor":null,
      "jew":null
    },
    "recruit":["步兵","卫兵","狮鹫","天使"],
    "inj":"asset/effect/injured-man.mp3"
  },
  "自警团":{
    "type":"步兵",
    "avatar":"asset/image/avatar/face3c.gif",
    "avatars":{
      "hurt":"asset/image/avatar/face3d.gif"
    },
    "img": "asset/image/role/hero/common/mgif99.png",
    "imgs": {
      "active":"asset/image/role/hero/active/mgif99.gif",
      "battle":"asset/image/role/hero/battle/class96.gif"
    },
    "atk":26,
    "def":24,
    "mov":5,
    "mr":50,
    "mp":2,
    "range":1,
    "move":"run",
    "command":{
      "range":3,
      "atk":2,
      "def":4
    },
    "magic":[],
    "magic_atk":1,
    "magic_range":0,
    "equip":{
      "weapon":"大剑",
      "armor":"锁子甲",
      "jew":null
    },
    "inj":"asset/effect/injured-man.mp3"
  },
  "步兵指挥官":{
    "type":"步兵",
    "avatar":"asset/image/avatar/face36.gif",
    "avatars":{
      "hurt":"asset/image/avatar/face37.gif"
    },
    "img": "asset/image/role/hero/common/mgif99.png",
    "imgs": {
      "active":"asset/image/role/hero/active/mgif99.gif",
      "battle":"asset/image/role/hero/battle/class96.gif"
    },
    "atk":22,
    "def":19,
    "mov":5,
    "mr":50,
    "mp":0,
    "range":1,
    "move":"run",
    "command":{
      "range":2,
      "atk":0,
      "def":2
    },
    "magic":[],
    "magic_atk":1,
    "magic_range":0,
    "equip":{
      "weapon":null,
      "armor":null,
      "jew":null
    },
    "inj":"asset/effect/injured-man.mp3"
  },
  "司祭":{
    "type":"神官",
    "avatar":"asset/image/avatar/face42.gif",
    "avatars":{
      "hurt":"asset/image/avatar/face43.gif"
    },
    "img": "asset/image/role/hero/common/mgif9c.png",
    "imgs": {
      "active":"asset/image/role/hero/active/mgif9c.gif",
      "battle":"asset/image/role/hero/battle/class9c.gif"
    },
    "atk":28,
    "def":28,
    "mov":5,
    "mr":50,
    "mp":10,
    "range":1,
    "move":"run",
    "command":{
      "range":3,
      "atk":4,
      "def":6
    },
    "magic":["回复2"],
    "magic_atk":1,
    "magic_range":0,
    "equip":{
      "weapon":"战锤",
      "armor":"锁子甲",
      "jew":null
    },
    "inj":"asset/effect/injured-man.mp3"
  },
  "村民":{
    "type":"无",
    "avatar":"asset/image/avatar/face2f.gif",
    "avatars":{
      "hurt":"asset/image/avatar/face30.gif"
    },
    "img": "asset/image/role/hero/common/mgif2b.png",
    "imgs": {
      "active":"asset/image/role/hero/active/mgif2b.gif",
      "battle":"asset/image/role/hero/battle/class2b.gif"
    },
    "atk":20,
    "def":17,
    "mov":5,
    "mr":50,
    "mp":3,
    "range":1,
    "move":"run",
    "command":{
      "range":2,
      "atk":0,
      "def":4
    },
    "magic":[],
    "magic_atk":1,
    "magic_range":0,
    "equip":{
      "weapon":null,
      "armor":null,
      "jew":null
    },
    "inj":"asset/effect/injured-woman.mp3"
  }
}